Workbook

Sheet 說明
A1: 39彩金桶 經濟模型試算（框架版）
A3: 用途：上游賠率表到位後，把數字填進「輸入參數」的黃色格子，其他分頁自動算出每期平台損益、玩家回報率、兩種頭獎處理方案的差異。
A5: 顏色說明
A6: 藍字＋黃底：需要填寫或可調整的輸入值（目前多為「範例值」，不是決策）
A7: 黑字：公式，請勿手動修改
A9: 目前狀態
A10: ・上游成本與派彩（輸入參數 B11:B15）目前為 0，等賠率表。填入前，「單期試算」的平台淨利不具參考價值。
A11: ・① ② ③ 每注與每張結算的 energy 消耗，部分為 0（待測試網實測，系統架構 V3），目前 energy 成本偏低估。
A12: ・TRX 價格為範例值，使用時請填當前價格。
A14: 計算方式說明
A15: ・全部為「期望值」（長期平均）。單一期實際結果會上下波動，尤其中 3 碼與頭獎。
A16: ・方案一（沒人中頭獎 → 全額滾存）：長期穩定後，每期提撥進彩池的錢平均全部回到玩家手上，彩池平均規模較大。
... A24: ・範例獎金（5 / 8 / 35 USDT，每注 10 USDT）：依舊規則 500 / 800 / 3500 點等比例縮小，僅示範格式。

Sheet 輸入參數
A1: 輸入參數（黃底藍字可改）
A2: 項目 | B2: 數值 | C2: 單位 | D2: 說明／來源
A3: 每注金額 | B3: 10 | C3: USDT | D3: 範例值，非決策
A4: 中 1 碼固定獎金 | B4: 5 | C4: USDT | D4: 範例值（舊規則 500 點等比例縮小）
A5: 中 2 碼獎金 | B5: 8 | C5: USDT | D5: 範例值【待賠率表】
A6: 中 3 碼獎金 | B6: 35 | C6: USDT | D6: 範例值【待賠率表】
A7: 4 碼保底獎 | B7: 35 | C7: USDT | D7: 範例值；規則要求不得低於中 3 碼獎金【待賠率表】
A8: 頭獎提撥比例 | B8: 0.1 | C8: % / 每注 | D8: 每注進頭獎彩池的比例；範例值
A9: 推廣分潤 第一層 | B9: 0.02 | C9: % / 每注 | D9: 範例值
A10: 推廣分潤 第二層 | B10: 0.01 | C10: % / 每注 | D10: 範例值
A11: 上游：每張柱單下注成本 | B11: 0 | C11: USDT | D11: 【待賠率表】一張 5 碼柱單轉上游的總成本
A12: 上游：中 2 碼時派彩 | B12: 0 | C12: USDT | D12: 【待賠率表】該張柱單在上游可回收的總額
A13: 上游：中 3 碼時派彩 | B13: 0 | C13: USDT | D13: 【待賠率表】
A14: 上游：中 4 碼時派彩 | B14: 0 | C14: USDT | D14: 【待賠率表】
... A27: 每次搬移 energy | B27: 64285 | C27: energy | D27: USDT 轉帳（收款方已有 USDT，主網實測）
A28: 下注方式佔比合計（須為 100%） | B28: =B16+B17+B18 | D28: =IF(ABS(B28-1)<0.0001,"OK","請修正：合計不是 100%")
A29: 平台份額比例（扣除頭獎提撥與分潤） | B29: =1-B8-B9-B10

Sheet 機率
A1: 每張柱單中獎機率（39 選 5、開 5 個）
A2: 中幾碼 | B2: 組合數 | C2: 機率 | D2: 約每幾張中一次
A3: 0 | B3: =1*((34*33*32*31*30)/(1*2*3*4*5)) | C3: =B3/((39*38*37*36*35)/(1*2*3*4*5)) | D3: =IF(C3>0,1/C3,0)
A4: 1 | B4: =((5)/(1))*((34*33*32*31)/(1*2*3*4)) | C4: =B4/((39*38*37*36*35)/(1*2*3*4*5)) | D4: =IF(C4>0,1/C4,0)
A5: 2 | B5: =((5*4)/(1*2))*((34*33*32)/(1*2*3)) | C5: =B5/((39*38*37*36*35)/(1*2*3*4*5)) | D5: =IF(C5>0,1/C5,0)
A6: 3 | B6: =((5*4*3)/(1*2*3))*((34*33)/(1*2)) | C6: =B6/((39*38*37*36*35)/(1*2*3*4*5)) | D6: =IF(C6>0,1/C6,0)
A7: 4 | B7: =((5*4*3*2)/(1*2*3*4))*((34)/(1)) | C7: =B7/((39*38*37*36*35)/(1*2*3*4*5)) | D7: =IF(C7>0,1/C7,0)
A8: 5 | B8: =((5*4*3*2*1)/(1*2*3*4*5))*1 | C8: =B8/((39*38*37*36*35)/(1*2*3*4*5)) | D8: =IF(C8>0,1/C8,0)
A9: 合計 | B9: =SUM(B3:B8) | C9: =SUM(C3:C8)
A10: 中 4 碼以上 | C10: =C7+C8 | D10: =1/C10
A11: 中 2 碼以上（上游有派彩） | C11: =C5+C6+C7+C8
A12: 中 0–1 碼（上游無派彩） | C12: =C3+C4
A14: 每期柱單數 vs 該期有人中頭獎（4 碼以上）的機率
A15: 每期柱單數 | B15: 有人中機率 | C15: 沒人中機率
A16: 100 | B16: =1-(1-$C$10)^A16 | C16: =(1-$C$10)^A16
A17: 300 | B17: =1-(1-$C$10)^A17 | C17: =(1-$C$10)^A17
A18: 500 | B18: =1-(1-$C$10)^A18 | C18: =(1-$C$10)^A18
A19: 1000 | B19: =1-(1-$C$10)^A19 | C19: =(1-$C$10)^A19
A20: 2000 | B20: =1-(1-$C$10)^A20 | C20: =(1-$C$10)^A20
A21: 3000 | B21: =1-(1-$C$10)^A21 | C21: =(1-$C$10)^A21
A22: 5000 | B22: =1-(1-$C$10)^A22 | C22: =(1-$C$10)^A22
A23: 10000 | B23: =1-(1-$C$10)^A23 | C23: =(1-$C$10)^A23

Sheet 單期試算
A1: 單期損益試算（期望值，單位 USDT）
A2: 每一欄是一種每期柱單數情境；第 3 列黃格可改。
A3: 每期柱單數 | B3: 500 | C3: 1000 | D3: 3000 | E3: 5000
A4: 下注總額 | B4: =B3*'輸入參數'!$B$3 | C4: =C3*'輸入參數'!$B$3 | D4: =D3*'輸入參數'!$B$3 | E4: =E3*'輸入參數'!$B$3
A6: 【資金分配】
A7: 進頭獎彩池（提撥） | B7: =B4*'輸入參數'!$B$8 | C7: =C4*'輸入參數'!$B$8 | D7: =D4*'輸入參數'!$B$8 | E7: =E4*'輸入參數'!$B$8
A8: 推廣分潤 | B8: =B4*('輸入參數'!$B$9+'輸入參數'!$B$10) | C8: =C4*('輸入參數'!$B$9+'輸入參數'!$B$10) | D8: =D4*('輸入參數'!$B$9+'輸入參數'!$B$10) | E8: =E4*('輸入參數'!$B$9+'輸入參數'!$B$10)
A9: 平台份額 | B9: =B4-B7-B8 | C9: =C4-C7-C8 | D9: =D4-D7-D8 | E9: =E4-E7-E8
A11: 【平台支出】
A12: 上游下注成本 | B12: =B3*'輸入參數'!$B$11 | C12: =C3*'輸入參數'!$B$11 | D12: =D3*'輸入參數'!$B$11 | E12: =E3*'輸入參數'!$B$11
A13: 固定獎金（中 1–3 碼） | B13: =B3*('機率'!$C$4*'輸入參數'!$B$4+'機率'!$C$5*'輸入參數'!$B$5+'機率'!$C$6*'輸入參數'!$B$6) | C13: =C3*('機率'!$C$4*'輸入參數'!$B$4+'機率'!$C$5*'輸入參數'!$B$5+'機率'!$C$6*'輸入參數'!$B$6) | D13: =D3*('機率'!$C$4*'輸入參數'!$B$4+'機率'!$C$5*'輸入參數'!$B$5+'機率'!$C$6*'輸入參數'!$B$6) | E13: =E3*('機率'!$C$4*'輸入參數'!$B$4+'機率'!$C$5*'輸入參數'!$B$5+'機率'!$C$6*'輸入參數'!$B$6)
A14: 4 碼保底獎（近似） | B14: =B3*'機率'!$C$7*(1-(1-'機率'!$C$8)^B3)*'輸入參數'!$B$7 | C14: =C3*'機率'!$C$7*(1-(1-'機率'!$C$8)^C3)*'輸入參數'!$B$7 | D14: =D3*'機率'!$C$7*(1-(1-'機率'!$C$8)^D3)*'輸入參數'!$B$7 | E14: =E3*'機率'!$C$7*(1-(1-'機率'!$C$8)^E3)*'輸入參數'!$B$7
A15: energy 代付（含 ② 自動派獎、每期搬移） | B15: =((B3*('輸入參數'!$B$16*'輸入參數'!$B$21+'輸入參數'!$B$17*'輸入參數'!$B$22+'輸入參數'!$B$18*'輸入參數'!$B$23+'輸入參數'!$B$24))+(B3*'輸入參數'!$B$17*('機率'!$C$4+'機率'!$C$5+'機率'!$C$6+'機率'!$C$7+'機率'!$C$8)*'輸入參數'!$B$25)+('輸入參數'!$B$26*'輸入參數'!$B$27))*'輸入參數'!$B$19/1000000*'輸入參數'!$B$20 | C15: =((C3*('輸入參數'!$B$16*'輸入參數'!$B$21+'輸入參數'!$B$17*'輸入參數'!$B$22+'輸入參數'!$B$18*'輸入參數'!$B$23+'輸入參數'!$B$24))+(C3*'輸入參數'!$B$17*('機率'!$C$4+'機率'!$C$5+'機率'!$C$6+'機率'!$C$7+'機率'!$C$8)*'輸入參數'!$B$25)+('輸入參數'!$B$26*'輸入參數'!$B$27))*'輸入參數'!$B$19/1000000*'輸入參數'!$B$20 | D15: =((D3*('輸入參數'!$B$16*'輸入參數'!$B$21+'輸入參數'!$B$17*'輸入參數'!$B$22+'輸入參數'!$B$18*'輸入參數'!$B$23+'輸入參數'!$B$24))+(D3*'輸入參數'!$B$17*('機率'!$C$4+'機率'!$C$5+'機率'!$C$6+'機率'!$C$7+'機率'!$C$8)*'輸入參數'!$B$25)+('輸入參數'!$B$26*'輸入參數'!$B$27))*'輸入參數'!$B$19/1000000*'輸入參數'!$B$20 | E15: =((E3*('輸入參數'!$B$16*'輸入參數'!$B$21+'輸入參數'!$B$17*'輸入參數'!$B$22+'輸入參數'!$B$18*'輸入參數'!$B$23+'輸入參數'!$B$24))+(E3*'輸入參數'!$B$17*('機率'!$C$4+'機率'!$C$5+'機率'!$C$6+'機率'!$C$7+'機率'!$C$8)*'輸入參數'!$B$25)+('輸入參數'!$B$26*'輸入參數'!$B$27))*'輸入參數'!$B$19/1000000*'輸入參數'!$B$20
A16: 支出合計 | B16: =B12+B13+B14+B15 | C16: =C12+C13+C14+C15 | D16: =D12+D13+D14+D15 | E16: =E12+E13+E14+E15
A18: 【平台收入】
A19: 上游回收（中 2 碼以上） | B19: =B3*('機率'!$C$5*'輸入參數'!$B$12+'機率'!$C$6*'輸入參數'!$B$13+'機率'!$C$7*'輸入參數'!$B$14+'機率'!$C$8*'輸入參數'!$B$15) | C19: =C3*('機率'!$C$5*'輸入參數'!$B$12+'機率'!$C$6*'輸入參數'!$B$13+'機率'!$C$7*'輸入參數'!$B$14+'機率'!$C$8*'輸入參數'!$B$15) | D19: =D3*('機率'!$C$5*'輸入參數'!$B$12+'機率'!$C$6*'輸入參數'!$B$13+'機率'!$C$7*'輸入參數'!$B$14+'機率'!$C$8*'輸入參數'!$B$15) | E19: =E3*('機率'!$C$5*'輸入參數'!$B$12+'機率'!$C$6*'輸入參數'!$B$13+'機率'!$C$7*'輸入參數'!$B$14+'機率'!$C$8*'輸入參數'!$B$15)
A21: 【頭獎彩池】
A22: 該期有人中頭獎機率 | B22: =1-(1-'機率'!$C$10)^B3 | C22: =1-(1-'機率'!$C$10)^C3 | D22: =1-(1-'機率'!$C$10)^D3 | E22: =1-(1-'機率'!$C$10)^E3
A23: 方案一：開獎時平均彩池規模 | B23: =IFERROR(B7/(0.8*B22),0) | C23: =IFERROR(C7/(0.8*C22),0) | D23: =IFERROR(D7/(0.8*D22),0) | E23: =IFERROR(E7/(0.8*E22),0)
A24: 方案二：開獎時平均彩池規模 | B24: =1.25*B7 | C24: =1.25*C7 | D24: =1.25*D7 | E24: =1.25*E7
A25: 方案二：平台平均每期收回 | B25: =(1-B22)*B7 | C25: =(1-C22)*C7 | D25: =(1-D22)*D7 | E25: =(1-E22)*E7
A27: 【結果】
A28: 平台淨利 — 方案一（全額滾存） | B28: =B9+B19-B16 | C28: =C9+C19-C16 | D28: =D9+D19-D16 | E28: =E9+E19-E16
A29: 平台淨利 — 方案二（留 20% 其餘歸平台） | B29: =B28+B25 | C29: =C28+C25 | D29: =D28+D25 | E29: =E28+E25
A30: 平台淨利率 — 方案一 | B30: =IFERROR(B28/B4,0) | C30: =IFERROR(C28/C4,0) | D30: =IFERROR(D28/D4,0) | E30: =IFERROR(E28/E4,0)
A31: 平台淨利率 — 方案二 | B31: =IFERROR(B29/B4,0) | C31: =IFERROR(C29/C4,0) | D31: =IFERROR(D29/D4,0) | E31: =IFERROR(E29/E4,0)
A32: 玩家回報率 — 方案一 | B32: =IFERROR((B13+B14+B7)/B4,0) | C32: =IFERROR((C13+C14+C7)/C4,0) | D32: =IFERROR((D13+D14+D7)/D4,0) | E32: =IFERROR((E13+E14+E7)/E4,0)
A33: 玩家回報率 — 方案二 | B33: =IFERROR((B13+B14+B22*B7)/B4,0) | C33: =IFERROR((C13+C14+C22*C7)/C4,0) | D33: =IFERROR((D13+D14+D22*D7)/D4,0) | E33: =IFERROR((E13+E14+E22*E7)/E4,0)
A34: 每注平台淨利 — 方案一 | B34: =IFERROR(B28/B3,0) | C34: =IFERROR(C28/C3,0) | D34: =IFERROR(D28/D3,0) | E34: =IFERROR(E28/E3,0)
A35: 每注平台淨利 — 方案二 | B35: =IFERROR(B29/B3,0) | C35: =IFERROR(C29/C3,0) | D35: =IFERROR(D29/D3,0) | E35: =IFERROR(E29/E3,0)
A37: 提醒：上游成本與派彩尚未填入（皆為 0），上方淨利目前不具參考價值。
